bgtask/__init__.py
bgtask/admin.py
bgtask/apps.py
bgtask/backends/__init__.py
bgtask/backends/thread_pool.py
bgtask/decorators.py
bgtask/migrations/0001_initial.py
bgtask/migrations/0002_backgroundtask_namespace_alter_backgroundtask_name.py
bgtask/migrations/__init__.py
bgtask/model_admin.py
bgtask/models.py
bgtask/stack_contexts.py
bgtask/static/bgtask/js/bgtask-once.js
bgtask/static/bgtask/js/bgtask.js
bgtask/templates/bgtask/admin/change_list.html
bgtask/templates/bgtask/bg_changelist_status_column.html
bgtask/templates/bgtask/bg_completed_column.html
bgtask/templates/bgtask/bgtask_templates.html
bgtask/templates/bgtask/bgtask_view.html
bgtask/templates/bgtask/progress.html
bgtask/templatetags/__init__.py
bgtask/templatetags/bgtask.py
bgtask/tests/test_bgtask.py
bgtask/urls.py
bgtask/views.py
django_admin_background_task-0.3.2.dist-info/LICENSE
django_admin_background_task-0.3.2.dist-info/METADATA
django_admin_background_task-0.3.2.dist-info/WHEEL
django_admin_background_task-0.3.2.dist-info/RECORD
