Metadata-Version: 2.1
Name: django-admin-background-task
Version: 0.3.2
Summary: A set of tools for django apps to persist and monitor the status of background tasks
Home-page: https://github.com/daphtdazz/django-bgtask
License: Apache-2.0
Author: David Park
Author-email: david@greenparksoftware.co.uk
Requires-Python: >=3.11,<4.0
Classifier: License :: OSI Approved :: Apache Software License
Classifier: Programming Language :: Python :: 3
Classifier: Programming Language :: Python :: 3.11
Classifier: Programming Language :: Python :: 3.12
Provides-Extra: all
Requires-Dist: Django (>=4.2,<4.3) ; extra == "all"
Requires-Dist: django-model-utils (>=4.4.0,<4.5.0)
Project-URL: Repository, https://github.com/daphtdazz/django-bgtask
